fink_spins/__init__.py
fink_spins/conftest.py
fink_spins/generate_data.py
fink_spins/hertha.py
fink_spins/hertha_ztf.py
fink_spins/model.py
fink_spins/plots.py
fink_spins/ssoft.py
fink_spins/ssptools.py
notebooks/__init__.py
notebooks/figure_mask.py
notebooks/figure_setup.py
notebooks/ssptools.py
fink_spins-0.3.8.dist-info/LICENSE
fink_spins-0.3.8.dist-info/METADATA
fink_spins-0.3.8.dist-info/WHEEL
fink_spins-0.3.8.dist-info/top_level.txt
fink_spins-0.3.8.dist-info/RECORD
