Metadata-Version: 2.1
Name: fink-spins
Version: 0.3.8
Summary: Collection of useful functionalities used for asteroid spins
Home-page: https://github.com/astrolabsoftware/fink-spins
Author: JulienPeloton
Author-email: peloton@lal.in2p3.fr
Project-URL: Source, https://github.com/astrolabsoftware/fink-spins
Classifier: Programming Language :: Python :: 3.7
Classifier: License :: OSI Approved :: Apache Software License
Classifier: Operating System :: Unix
Classifier: Development Status :: 4 - Beta
Classifier: Intended Audience :: Science/Research
License-File: LICENSE
